bangunDatar/__init__.py
bangunDatar/belahketupat.py
bangunDatar/jajargenjang.py
bangunDatar/layanglayang.py
bangunDatar/lingkaran.py
bangunDatar/persegi.py
bangunDatar/segitiga.py
bangunDatar/trapesium.py
bangunRuang/balok.py
bangunRuang/bola.py
bangunRuang/kerucut.py
bangunRuang/kubus.py
bangunRuang/limas.py
bangunRuang/prisma.py
bangunRuang/tabung.py
Rumus_12-0.0.1.dist-info/LICENSE.txt
Rumus_12-0.0.1.dist-info/METADATA
Rumus_12-0.0.1.dist-info/WHEEL
Rumus_12-0.0.1.dist-info/top_level.txt
Rumus_12-0.0.1.dist-info/RECORD
