Metadata-Version: 2.1
Name: Rumus-12
Version: 0.0.1
Summary: Kumpulan rumus
Author: heybudie2
Author-email: <lhrbdipras2@gmail.com>
Classifier: Development Status :: 1 - Planning
Classifier: Intended Audience :: Developers
Classifier: Programming Language :: Python :: 3
Classifier: Operating System :: Microsoft :: Windows
License-File: LICENSE.txt
